[{"title":"Exponential Function Using Recursion","uid":"7c3e94c5688f33ead760d1d2b226acb0","slug":"exponential-function-using-recursion","date":"2022-01-07T19:46:31.000Z","updated":"2022-01-08T15:00:11.276Z","comments":true,"path":"api/articles/exponential-function-using-recursion.json","cover":"https://images.unsplash.com/photo-1635775017492-1eb935a082a4?ixlib=rb-1.2.1&ixid=MnwxMjA3fDB8MHxzZWFyY2h8Mnx8YyUyQiUyQnxlbnwwfHwwfHw%3D&auto=format&fit=crop&w=800&q=60","text":"double e(int m, int n)&#123; double r; static double p = 1, f = 1; if (n==0) &#123; return 1; &#125; else &#123; r = e(m, n-1); p = p*m; f =...","link":"","photos":[],"count_time":{"symbolsCount":681,"symbolsTime":"1 mins."},"categories":[{"name":"Note","slug":"Note","count":2,"path":"api/categories/Note.json"}],"tags":[{"name":"C/C++","slug":"C-C","count":5,"path":"api/tags/C-C.json"}],"author":{"name":"炭吉貓","slug":"blog-author","avatar":"https://jianan1104.github.io/avatar.gif","link":"/","description":"這隻貓很懶還在念研，所以什麼都沒留下！","socials":{"github":"","twitter":"","stackoverflow":"","wechat":"","qq":"","weibo":"","zhihu":"","csdn":"","juejin":"","customs":{}}},"feature":true},{"title":"C++ Template Example","uid":"cc8340e350d1479c3156650fc34ebe25","slug":"c-template-example","date":"2022-01-06T14:52:55.000Z","updated":"2022-01-06T14:55:14.203Z","comments":true,"path":"api/articles/c-template-example.json","cover":"https://images.unsplash.com/photo-1635775017492-1eb935a082a4?ixlib=rb-1.2.1&ixid=MnwxMjA3fDB8MHxzZWFyY2h8Mnx8YyUyQiUyQnxlbnwwfHwwfHw%3D&auto=format&fit=crop&w=800&q=60","text":"#include &lt;iostream&gt; using namespace std; template&lt;class T&gt; class math &#123; private: T a; T b; public: math(T a, T b); T add();...","link":"","photos":[],"count_time":{"symbolsCount":766,"symbolsTime":"1 mins."},"categories":[{"name":"Note","slug":"Note","count":2,"path":"api/categories/Note.json"}],"tags":[{"name":"C/C++","slug":"C-C","count":5,"path":"api/tags/C-C.json"},{"name":"Template","slug":"Template","count":1,"path":"api/tags/Template.json"}],"author":{"name":"炭吉貓","slug":"blog-author","avatar":"https://jianan1104.github.io/avatar.gif","link":"/","description":"這隻貓很懶還在念研，所以什麼都沒留下！","socials":{"github":"","twitter":"","stackoverflow":"","wechat":"","qq":"","weibo":"","zhihu":"","csdn":"","juejin":"","customs":{}}},"feature":true},{"title":"Power Using Recursion","uid":"124220062c4bd652db0019aa66f3a2a1","slug":"power-using-recursion","date":"2022-01-06T14:42:33.000Z","updated":"2022-01-08T15:00:46.303Z","comments":true,"path":"api/articles/power-using-recursion.json","cover":"https://images.unsplash.com/photo-1635775017492-1eb935a082a4?ixlib=rb-1.2.1&ixid=MnwxMjA3fDB8MHxzZWFyY2h8Mnx8YyUyQiUyQnxlbnwwfHwwfHw%3D&auto=format&fit=crop&w=800&q=60","text":"int power(int m, int n)&#123; if(n==0) return 1; else return power(m, n-1)*m; &#125; int main(int argc, const char * argv[]) &#123; printf(\"...","link":"","photos":[],"count_time":{"symbolsCount":487,"symbolsTime":"1 mins."},"categories":[{"name":"Algorithms","slug":"Algorithms","count":3,"path":"api/categories/Algorithms.json"}],"tags":[{"name":"C/C++","slug":"C-C","count":5,"path":"api/tags/C-C.json"},{"name":"Recursion","slug":"Recursion","count":3,"path":"api/tags/Recursion.json"}],"author":{"name":"炭吉貓","slug":"blog-author","avatar":"https://jianan1104.github.io/avatar.gif","link":"/","description":"這隻貓很懶還在念研，所以什麼都沒留下！","socials":{"github":"","twitter":"","stackoverflow":"","wechat":"","qq":"","weibo":"","zhihu":"","csdn":"","juejin":"","customs":{}}},"feature":true}]